talkapps_client/__init__.py
talkapps_client/errors.py
talkapps_client/stickersclient.py
talkapps_client/urls.py
talkapps_client/classes/Stickers_pb2.py
talkapps_client/classes/__init__.py
talkapps_client/classes/downloader.py
talkapps_client/classes/talkcrypto.py
talkapps_client/classes/uploader.py
talkapps_client/models/__init__.py
talkapps_client/models/local_sticker_pack.py
talkapps_client/models/sticker.py
talkapps_client/models/sticker_pack.py
talkapps_client/utils/__init__.py
talkapps_client/utils/ca/__init__.py
talkapps_client/utils/ca/ca.py
talkapps_client/utils/ca/cacert.pem
talkapps_client-3.1.0.dist-info/LICENSE
talkapps_client-3.1.0.dist-info/METADATA
talkapps_client-3.1.0.dist-info/WHEEL
talkapps_client-3.1.0.dist-info/top_level.txt
talkapps_client-3.1.0.dist-info/RECORD
