Metadata-Version: 2.1
Name: talkapps-client
Version: 3.1.0
Summary: A client for the Talk stickers API
Home-page: https://github.com/talkapps/talkapps-client
Author: NKDuy
Author-email: kn145660@gmail.com
License: UNKNOWN
Platform: UNKNOWN
Classifier: Programming Language :: Python :: 3
Classifier: License :: OSI Approved :: GNU Lesser General Public License v3 (LGPLv3)
Classifier: Operating System :: OS Independent
Classifier: Topic :: Communications :: Chat
Requires-Python: >=3.6
Requires-Dist: anyio (<3.0.0,>=2.0.2)
Requires-Dist: httpx (<0.17.0,>=0.16.1)
Requires-Dist: cryptography (<4.0.0,>=3.1.1)
Requires-Dist: protobuf (<4.0.0,>=3.13.0)
